olarmflowclient/__init__.py
olarmflowclient/const.py
olarmflowclient/olarmflowclient.py
olarmflowclient-1.0.2.dist-info/licenses/LICENSE
olarmflowclient-1.0.2.dist-info/METADATA
olarmflowclient-1.0.2.dist-info/WHEEL
olarmflowclient-1.0.2.dist-info/top_level.txt
olarmflowclient-1.0.2.dist-info/RECORD
