Metadata-Version: 2.4
Name: olarmflowclient
Version: 1.0.2
Summary: The official asynchronous Python client for the Olarm Public API.
Author-email: Olarm <support@olarm.com>
License-Expression: Apache-2.0
Project-URL: Homepage, https://www.olarm.com
Project-URL: Repository, https://github.com/olarmtech/olarmflowclient-python
Keywords: olarm,api,security,alarm,asyncio
Classifier: Programming Language :: Python :: 3
Classifier: Operating System :: OS Independent
Classifier: Intended Audience :: Developers
Classifier: Topic :: Home Automation
Classifier: Topic :: Software Development :: Libraries :: Python Modules
Requires-Python: >=3.10
License-File: LICENSE
Requires-Dist: aiohttp>=3.12.0
Requires-Dist: paho-mqtt>=2.1.0
Dynamic: license-file
